compare_hash/__init__.py
compare_hash/compare_hash.py
compare_hash-0.0.5.dist-info/METADATA
compare_hash-0.0.5.dist-info/WHEEL
compare_hash-0.0.5.dist-info/entry_points.txt
compare_hash-0.0.5.dist-info/top_level.txt
compare_hash-0.0.5.dist-info/RECORD
