Metadata-Version: 2.1
Name: compare-hash
Version: 0.0.5
Summary: Compare the contents of two folders
Home-page: https://github.com/jaytrairat/python-compare-hashes
Author: jaytrairat
Author-email: jaytrairat@outlook.com
Classifier: Programming Language :: Python :: 3
